ISCV/Aimousetracking.py
ISCV/FaceMesh.py
ISCV/FullBodyPosture.py
ISCV/HandModule.py
ISCV/__init__.py
ISCV-2.1.1.dist-info/METADATA
ISCV-2.1.1.dist-info/WHEEL
ISCV-2.1.1.dist-info/top_level.txt
ISCV-2.1.1.dist-info/RECORD
