Metadata-Version: 2.1
Name: ISCV
Version: 2.1.1
Summary: ISCV is a computer vision library.
Author: Mitansh Disha Meet Parnika
Author-email: <mitanshpanchal@gmail.com>
Keywords: python,video,stream,video stream,camera stream,sockets,computer vision,machine learning,AI
Classifier: Development Status :: 1 - Planning
Classifier: Intended Audience :: Developers
Classifier: Programming Language :: Python :: 3
Classifier: Operating System :: Unix
Classifier: Operating System :: MacOS :: MacOS X
Classifier: Operating System :: Microsoft :: Windows
Requires-Dist: opencv-python
Requires-Dist: pyautogui
Requires-Dist: numpy
Requires-Dist: mediapipe
